{
  "books": [
    {
      "name": "Truyện Cười",
      "desc": "haha",
      "id": "LbtIxH6f9"
    },
    {
      "name": "Truyện ma",
      "desc": "ma",
      "id": "tHOi-B5v6"
    },
    {
      "name": "Doraemon",
      "desc": "mon",
      "id": "Difaio03r"
    },
    {
      "name": "pikachu",
      "desc": "pika",
      "id": "SIaoGnsIB"
    }
  ],
  "users": [
    {
      "name": "Hy Khang",
      "phone": "0933308108",
      "id": "uIxAiwgQg",
      "email": "tranhykhang8108@gmail.com",
      "password": "hyhyk2209"
    },
    {
      "name": "Minh Thư",
      "phone": "0902907956",
      "email": "minhthu@gmail.com",
      "password": "123123",
      "id": "BnRtNtR5q"
    },
    {
      "name": "Hy Hy",
      "phone": "0909123456",
      "email": "hyhy@gmail.com",
      "password": "456456",
      "id": "SIYwsKcu1"
    },
    {
      "name": "Hy Hy Khang",
      "phone": "090809090808",
      "email": "hykhang@gmail.com",
      "password": "789789",
      "id": "vPnZelspW"
    },
    {
      "name": "Khang Hy",
      "phone": "0987654321",
      "email": "khanghy@gmail.com",
      "password": "229229",
      "id": "TFakyYxC3"
    },
    {
      "name": "hhhhhhhhhhhhhhhhhhhhhhhhhhh",
      "phone": "dsssssssssssssss",
      "email": "hahaha",
      "password": "4297f44b13955235245b2497399d7a93",
      "id": "isprWyO_Z"
    },
    {
      "name": "dsadsadasdasdasd",
      "phone": "00000000000000000",
      "email": "hyhykaka",
      "password": "123456123456",
      "id": "OZy5wiXRN"
    },
    {
      "name": "ddddddddddaaaaaaaaaaaaa",
      "phone": "dddddddddddddddddd",
      "email": "hyhykaka",
      "password": "$2b$10$904m54Ub4YKQUzTyWggB.eflrHm19dOQ42D3IXgOra/1Rpw3jgwxm",
      "id": "LLc6hRS1y"
    },
    {
      "name": "hy",
      "phone": "das",
      "email": "hy",
      "password": "$2b$10$K61WjESZGDvrnFRx9nK8eu.waznftzrKA24ZjQsiKsxo0WYJ99hq2",
      "wrongLoginCount": 0,
      "id": "Z0NlyWq8S"
    }
  ],
  "trans": [
    {
      "userName": "Hy Khang",
      "bookName": "Truyện Cười",
      "id": "uIxAiwgQg",
      "idBorrowed": "FVCYHJEu5",
      "isComplete": "true"
    },
    {
      "userName": "Hy Hy",
      "bookName": "Truyện Cười",
      "id": "SIYwsKcu1",
      "idBorrowed": "C8naWEwDs",
      "isComplete": "false"
    },
    {
      "userName": "Hy Khang",
      "bookName": "Truyện Cười",
      "id": "uIxAiwgQg",
      "idBorrowed": "TRHExjDT1",
      "isComplete": "false"
    }
  ]
}